{
  "cols": 2,
  "data": {
    "slice-0": [
      7168.0,
      6144.0
    ],
    "slice-1": [
      13312.0,
      29184.0
    ],
    "slice-10": [
      364032.0,
      55296.0
    ],
    "slice-100": [
      6966272.0,
      124416.0
    ],
    "slice-101": [
      7090688.0,
      57856.0
    ],
    "slice-102": [
      7148544.0,
      44032.0
    ],
    "slice-103": [
      7192576.0,
      12800.0
    ],
    "slice-104": [
      7205376.0,
      19456.0
    ],
    "slice-105": [
      7224832.0,
      38912.0
    ],
    "slice-106": [
      7263744.0,
      23552.0
    ],
    "slice-107": [
      7287296.0,
      40960.0
    ],
    "slice-108": [
      7328256.0,
      27648.0
    ],
    "slice-109": [
      7355904.0,
      62976.0
    ],
    "slice-11": [
      419328.0,
      6656.0
    ],
    "slice-110": [
      7418880.0,
      110080.0
    ],
    "slice-111": [
      7528960.0,
      19456.0
    ],
    "slice-112": [
      7548416.0,
      117760.0
    ],
    "slice-113": [
      7666176.0,
      48128.0
    ],
    "slice-114": [
      7714304.0,
      66560.0
    ],
    "slice-115": [
      7780864.0,
      30208.0
    ],
    "slice-116": [
      7811072.0,
      50688.0
    ],
    "slice-117": [
      7861760.0,
      11264.0
    ],
    "slice-118": [
      7873024.0,
      8704.0
    ],
    "slice-119": [
      7881728.0,
      5632.0
    ],
    "slice-12": [
      425984.0,
      25600.0
    ],
    "slice-120": [
      7887360.0,
      8192.0
    ],
    "slice-121": [
      7895552.0,
      24576.0
    ],
    "slice-122": [
      7920128.0,
      15872.0
    ],
    "slice-123": [
      7936000.0,
      83456.0
    ],
    "slice-124": [
      8019456.0,
      22528.0
    ],
    "slice-125": [
      8041984.0,
      11776.0
    ],
    "slice-126": [
      8053760.0,
      71680.0
    ],
    "slice-127": [
      8125440.0,
      33280.0
    ],
    "slice-128": [
      8158720.0,
      44032.0
    ],
    "slice-129": [
      8202752.0,
      15872.0
    ],
    "slice-13": [
      451584.0,
      54272.0
    ],
    "slice-130": [
      8218624.0,
      46592.0
    ],
    "slice-131": [
      8265216.0,
      11776.0
    ],
    "slice-132": [
      8276992.0,
      42496.0
    ],
    "slice-133": [
      8319488.0,
      180736.0
    ],
    "slice-134": [
      8500224.0,
      6144.0
    ],
    "slice-135": [
      8506368.0,
      14848.0
    ],
    "slice-136": [
      8521216.0,
      5632.0
    ],
    "slice-137": [
      8526848.0,
      15872.0
    ],
    "slice-138": [
      8542720.0,
      17408.0
    ],
    "slice-139": [
      8560128.0,
      18944.0
    ],
    "slice-14": [
      505856.0,
      6656.0
    ],
    "slice-140": [
      8579072.0,
      29184.0
    ],
    "slice-141": [
      8608256.0,
      16384.0
    ],
    "slice-142": [
      8624640.0,
      41984.0
    ],
    "slice-143": [
      8666624.0,
      20992.0
    ],
    "slice-144": [
      8687616.0,
      35328.0
    ],
    "slice-145": [
      8722944.0,
      11264.0
    ],
    "slice-146": [
      8734208.0,
      14848.0
    ],
    "slice-147": [
      8749056.0,
      15360.0
    ],
    "slice-148": [
      8764416.0,
      27648.0
    ],
    "slice-149": [
      8792064.0,
      10240.0
    ],
    "slice-15": [
      512512.0,
      112128.0
    ],
    "slice-150": [
      8802304.0,
      17920.0
    ],
    "slice-151": [
      8820224.0,
      9728.0
    ],
    "slice-152": [
      8829952.0,
      5632.0
    ],
    "slice-153": [
      8835584.0,
      25600.0
    ],
    "slice-154": [
      8861184.0,
      22016.0
    ],
    "slice-155": [
      8883200.0,
      14848.0
    ],
    "slice-156": [
      8898048.0,
      20992.0
    ],
    "slice-157": [
      8919040.0,
      38400.0
    ],
    "slice-158": [
      8957440.0,
      35840.0
    ],
    "slice-159": [
      8993280.0,
      14848.0
    ],
    "slice-16": [
      624640.0,
      19456.0
    ],
    "slice-160": [
      9008128.0,
      6656.0
    ],
    "slice-161": [
      9014784.0,
      11264.0
    ],
    "slice-162": [
      9026048.0,
      16384.0
    ],
    "slice-163": [
      9042432.0,
      15872.0
    ],
    "slice-164": [
      9058304.0,
      19456.0
    ],
    "slice-165": [
      9077760.0,
      5632.0
    ],
    "slice-166": [
      9083392.0,
      23040.0
    ],
    "slice-167": [
      9106432.0,
      17408.0
    ],
    "slice-168": [
      9123840.0,
      18944.0
    ],
    "slice-169": [
      9142784.0,
      86016.0
    ],
    "slice-17": [
      644096.0,
      10240.0
    ],
    "slice-170": [
      9228800.0,
      9728.0
    ],
    "slice-171": [
      9238528.0,
      23552.0
    ],
    "slice-172": [
      9262080.0,
      53760.0
    ],
    "slice-173": [
      9315840.0,
      78336.0
    ],
    "slice-174": [
      9394176.0,
      10240.0
    ],
    "slice-175": [
      9404416.0,
      73728.0
    ],
    "slice-176": [
      9478144.0,
      14336.0
    ],
    "slice-177": [
      9492480.0,
      79360.0
    ],
    "slice-178": [
      9571840.0,
      10240.0
    ],
    "slice-179": [
      9582080.0,
      12800.0
    ],
    "slice-18": [
      654336.0,
      17408.0
    ],
    "slice-180": [
      9594880.0,
      62464.0
    ],
    "slice-181": [
      9657344.0,
      34816.0
    ],
    "slice-182": [
      9692160.0,
      7168.0
    ],
    "slice-183": [
      9699328.0,
      104448.0
    ],
    "slice-184": [
      9803776.0,
      19456.0
    ],
    "slice-185": [
      9823232.0,
      82944.0
    ],
    "slice-186": [
      9906176.0,
      57344.0
    ],
    "slice-187": [
      9963520.0,
      8192.0
    ],
    "slice-188": [
      9971712.0,
      20480.0
    ],
    "slice-189": [
      9992192.0,
      81920.0
    ],
    "slice-19": [
      671744.0,
      6656.0
    ],
    "slice-190": [
      10074112.0,
      54272.0
    ],
    "slice-191": [
      10128384.0,
      24064.0
    ],
    "slice-192": [
      10152448.0,
      6144.0
    ],
    "slice-193": [
      10158592.0,
      165376.0
    ],
    "slice-194": [
      10323968.0,
      19456.0
    ],
    "slice-195": [
      10343424.0,
      24064.0
    ],
    "slice-196": [
      10367488.0,
      39424.0
    ],
    "slice-197": [
      10406912.0,
      6144.0
    ],
    "slice-198": [
      10413056.0,
      117760.0
    ],
    "slice-199": [
      10530816.0,
      13312.0
    ],
    "slice-2": [
      42496.0,
      9728.0
    ],
    "slice-20": [
      678400.0,
      13312.0
    ],
    "slice-200": [
      10544128.0,
      35840.0
    ],
    "slice-201": [
      10579968.0,
      24064.0
    ],
    "slice-202": [
      10604032.0,
      20992.0
    ],
    "slice-203": [
      10625024.0,
      22016.0
    ],
    "slice-204": [
      10647040.0,
      176640.0
    ],
    "slice-205": [
      10823680.0,
      143872.0
    ],
    "slice-206": [
      10967552.0,
      74752.0
    ],
    "slice-207": [
      11042304.0,
      100864.0
    ],
    "slice-208": [
      11143168.0,
      35840.0
    ],
    "slice-209": [
      11179008.0,
      6656.0
    ],
    "slice-21": [
      691712.0,
      7168.0
    ],
    "slice-210": [
      11185664.0,
      6144.0
    ],
    "slice-211": [
      11191808.0,
      129536.0
    ],
    "slice-212": [
      11321344.0,
      48640.0
    ],
    "slice-213": [
      11369984.0,
      8704.0
    ],
    "slice-214": [
      11378688.0,
      93184.0
    ],
    "slice-215": [
      11471872.0,
      7168.0
    ],
    "slice-216": [
      11479040.0,
      7168.0
    ],
    "slice-217": [
      11486208.0,
      24576.0
    ],
    "slice-218": [
      11510784.0,
      6656.0
    ],
    "slice-219": [
      11517440.0,
      201728.0
    ],
    "slice-22": [
      698880.0,
      19456.0
    ],
    "slice-220": [
      11719168.0,
      8192.0
    ],
    "slice-221": [
      11727360.0,
      21504.0
    ],
    "slice-222": [
      11748864.0,
      127488.0
    ],
    "slice-223": [
      11876352.0,
      68096.0
    ],
    "slice-224": [
      11944448.0,
      10752.0
    ],
    "slice-225": [
      11955200.0,
      13824.0
    ],
    "slice-226": [
      11969024.0,
      10752.0
    ],
    "slice-227": [
      11979776.0,
      15360.0
    ],
    "slice-228": [
      11995136.0,
      29696.0
    ],
    "slice-229": [
      12024832.0,
      141824.0
    ],
    "slice-23": [
      718336.0,
      27648.0
    ],
    "slice-230": [
      12166656.0,
      6144.0
    ],
    "slice-231": [
      12172800.0,
      75264.0
    ],
    "slice-232": [
      12248064.0,
      22016.0
    ],
    "slice-233": [
      12270080.0,
      164352.0
    ],
    "slice-234": [
      12434432.0,
      9216.0
    ],
    "slice-235": [
      12443648.0,
      108032.0
    ],
    "slice-236": [
      12551680.0,
      58880.0
    ],
    "slice-237": [
      12610560.0,
      13312.0
    ],
    "slice-238": [
      12623872.0,
      18944.0
    ],
    "slice-239": [
      12642816.0,
      55808.0
    ],
    "slice-24": [
      745984.0,
      17408.0
    ],
    "slice-240": [
      12698624.0,
      14336.0
    ],
    "slice-241": [
      12712960.0,
      6656.0
    ],
    "slice-242": [
      12719616.0,
      77312.0
    ],
    "slice-243": [
      12796928.0,
      19456.0
    ],
    "slice-244": [
      12816384.0,
      24064.0
    ],
    "slice-245": [
      12840448.0,
      37888.0
    ],
    "slice-246": [
      12878336.0,
      146432.0
    ],
    "slice-247": [
      13024768.0,
      30208.0
    ],
    "slice-248": [
      13054976.0,
      6144.0
    ],
    "slice-249": [
      13061120.0,
      12288.0
    ],
    "slice-25": [
      763392.0,
      130048.0
    ],
    "slice-250": [
      13073408.0,
      12800.0
    ],
    "slice-251": [
      13086208.0,
      179200.0
    ],
    "slice-252": [
      13265408.0,
      8704.0
    ],
    "slice-253": [
      13274112.0,
      13312.0
    ],
    "slice-254": [
      13287424.0,
      10240.0
    ],
    "slice-255": [
      13297664.0,
      7680.0
    ],
    "slice-256": [
      13305344.0,
      11264.0
    ],
    "slice-257": [
      13316608.0,
      6656.0
    ],
    "slice-258": [
      13323264.0,
      94720.0
    ],
    "slice-259": [
      13417984.0,
      28672.0
    ],
    "slice-26": [
      893440.0,
      57344.0
    ],
    "slice-260": [
      13446656.0,
      70656.0
    ],
    "slice-261": [
      13517312.0,
      118784.0
    ],
    "slice-262": [
      13636096.0,
      8192.0
    ],
    "slice-263": [
      13644288.0,
      82432.0
    ],
    "slice-264": [
      13726720.0,
      6656.0
    ],
    "slice-265": [
      13733376.0,
      7680.0
    ],
    "slice-266": [
      13741056.0,
      26112.0
    ],
    "slice-267": [
      13767168.0,
      9216.0
    ],
    "slice-268": [
      13776384.0,
      5632.0
    ],
    "slice-269": [
      13782016.0,
      196608.0
    ],
    "slice-27": [
      950784.0,
      77312.0
    ],
    "slice-270": [
      13978624.0,
      10240.0
    ],
    "slice-271": [
      13988864.0,
      9216.0
    ],
    "slice-272": [
      13998080.0,
      128512.0
    ],
    "slice-273": [
      14126592.0,
      27136.0
    ],
    "slice-274": [
      14153728.0,
      9216.0
    ],
    "slice-275": [
      14162944.0,
      171520.0
    ],
    "slice-276": [
      14334464.0,
      6144.0
    ],
    "slice-277": [
      14340608.0,
      36352.0
    ],
    "slice-278": [
      14376960.0,
      15872.0
    ],
    "slice-279": [
      14392832.0,
      11776.0
    ],
    "slice-28": [
      1028096.0,
      102912.0
    ],
    "slice-280": [
      14404608.0,
      26112.0
    ],
    "slice-281": [
      14430720.0,
      7680.0
    ],
    "slice-282": [
      14438400.0,
      5632.0
    ],
    "slice-283": [
      14444032.0,
      16384.0
    ],
    "slice-284": [
      14460416.0,
      15872.0
    ],
    "slice-285": [
      14476288.0,
      148992.0
    ],
    "slice-286": [
      14625280.0,
      109056.0
    ],
    "slice-287": [
      14734336.0,
      7168.0
    ],
    "slice-288": [
      14741504.0,
      13824.0
    ],
    "slice-289": [
      14755328.0,
      16896.0
    ],
    "slice-29": [
      1131008.0,
      114176.0
    ],
    "slice-290": [
      14772224.0,
      33280.0
    ],
    "slice-291": [
      14805504.0,
      254464.0
    ],
    "slice-292": [
      15059968.0,
      25600.0
    ],
    "slice-293": [
      15085568.0,
      6656.0
    ],
    "slice-294": [
      15092224.0,
      11776.0
    ],
    "slice-295": [
      15104000.0,
      121344.0
    ],
    "slice-296": [
      15225344.0,
      75776.0
    ],
    "slice-297": [
      15301120.0,
      24576.0
    ],
    "slice-298": [
      15325696.0,
      30720.0
    ],
    "slice-299": [
      15356416.0,
      24576.0
    ],
    "slice-3": [
      52224.0,
      16384.0
    ],
    "slice-30": [
      1245184.0,
      43008.0
    ],
    "slice-300": [
      15380992.0,
      18944.0
    ],
    "slice-301": [
      15399936.0,
      60928.0
    ],
    "slice-302": [
      15460864.0,
      16896.0
    ],
    "slice-303": [
      15477760.0,
      76800.0
    ],
    "slice-304": [
      15554560.0,
      55808.0
    ],
    "slice-305": [
      15610368.0,
      15872.0
    ],
    "slice-306": [
      15626240.0,
      7680.0
    ],
    "slice-307": [
      15633920.0,
      11776.0
    ],
    "slice-308": [
      15645696.0,
      12800.0
    ],
    "slice-309": [
      15658496.0,
      43008.0
    ],
    "slice-31": [
      1288192.0,
      113664.0
    ],
    "slice-310": [
      15701504.0,
      14848.0
    ],
    "slice-311": [
      15716352.0,
      46592.0
    ],
    "slice-312": [
      15762944.0,
      25088.0
    ],
    "slice-313": [
      15788032.0,
      34816.0
    ],
    "slice-314": [
      15822848.0,
      19968.0
    ],
    "slice-315": [
      15842816.0,
      17920.0
    ],
    "slice-316": [
      15860736.0,
      13824.0
    ],
    "slice-317": [
      15874560.0,
      21504.0
    ],
    "slice-318": [
      15896064.0,
      26112.0
    ],
    "slice-319": [
      15922176.0,
      16896.0
    ],
    "slice-32": [
      1401856.0,
      140288.0
    ],
    "slice-320": [
      15939072.0,
      25600.0
    ],
    "slice-321": [
      15964672.0,
      17920.0
    ],
    "slice-322": [
      15982592.0,
      12800.0
    ],
    "slice-323": [
      15995392.0,
      7680.0
    ],
    "slice-324": [
      16003072.0,
      25088.0
    ],
    "slice-325": [
      16028160.0,
      8704.0
    ],
    "slice-326": [
      16036864.0,
      6144.0
    ],
    "slice-327": [
      16043008.0,
      6656.0
    ],
    "slice-328": [
      16049664.0,
      17920.0
    ],
    "slice-329": [
      16067584.0,
      7680.0
    ],
    "slice-33": [
      1542144.0,
      13824.0
    ],
    "slice-330": [
      16075264.0,
      10752.0
    ],
    "slice-331": [
      16086016.0,
      16384.0
    ],
    "slice-332": [
      16102400.0,
      14336.0
    ],
    "slice-333": [
      16116736.0,
      25088.0
    ],
    "slice-334": [
      16141824.0,
      30208.0
    ],
    "slice-335": [
      16172032.0,
      10240.0
    ],
    "slice-336": [
      16182272.0,
      28672.0
    ],
    "slice-337": [
      16210944.0,
      137728.0
    ],
    "slice-338": [
      16348672.0,
      24064.0
    ],
    "slice-339": [
      16372736.0,
      9728.0
    ],
    "slice-34": [
      1555968.0,
      112128.0
    ],
    "slice-340": [
      16382464.0,
      10752.0
    ],
    "slice-341": [
      16393216.0,
      19456.0
    ],
    "slice-342": [
      16412672.0,
      9216.0
    ],
    "slice-343": [
      16421888.0,
      215552.0
    ],
    "slice-344": [
      16637440.0,
      13824.0
    ],
    "slice-345": [
      16651264.0,
      9728.0
    ],
    "slice-346": [
      16660992.0,
      6144.0
    ],
    "slice-347": [
      16667136.0,
      10240.0
    ],
    "slice-348": [
      16677376.0,
      11264.0
    ],
    "slice-349": [
      16688640.0,
      34304.0
    ],
    "slice-35": [
      1668096.0,
      195072.0
    ],
    "slice-350": [
      16722944.0,
      37376.0
    ],
    "slice-351": [
      16760320.0,
      132096.0
    ],
    "slice-352": [
      16892416.0,
      113664.0
    ],
    "slice-353": [
      17006080.0,
      39424.0
    ],
    "slice-354": [
      17045504.0,
      18944.0
    ],
    "slice-355": [
      17064448.0,
      8192.0
    ],
    "slice-356": [
      17072640.0,
      8192.0
    ],
    "slice-357": [
      17080832.0,
      91648.0
    ],
    "slice-358": [
      17172480.0,
      11776.0
    ],
    "slice-359": [
      17184256.0,
      40960.0
    ],
    "slice-36": [
      1863168.0,
      11776.0
    ],
    "slice-360": [
      17225216.0,
      5632.0
    ],
    "slice-361": [
      17230848.0,
      82432.0
    ],
    "slice-362": [
      17313280.0,
      116224.0
    ],
    "slice-363": [
      17429504.0,
      62464.0
    ],
    "slice-364": [
      17491968.0,
      131584.0
    ],
    "slice-365": [
      17623552.0,
      55808.0
    ],
    "slice-366": [
      17679360.0,
      14336.0
    ],
    "slice-367": [
      17693696.0,
      287744.0
    ],
    "slice-368": [
      17981440.0,
      9216.0
    ],
    "slice-369": [
      17990656.0,
      22528.0
    ],
    "slice-37": [
      1874944.0,
      8704.0
    ],
    "slice-370": [
      18013184.0,
      29696.0
    ],
    "slice-371": [
      18042880.0,
      385024.0
    ],
    "slice-372": [
      18427904.0,
      22528.0
    ],
    "slice-373": [
      18450432.0,
      27136.0
    ],
    "slice-374": [
      18477568.0,
      207360.0
    ],
    "slice-375": [
      18684928.0,
      20992.0
    ],
    "slice-376": [
      18705920.0,
      13312.0
    ],
    "slice-377": [
      18719232.0,
      7680.0
    ],
    "slice-378": [
      18726912.0,
      15872.0
    ],
    "slice-379": [
      18742784.0,
      20480.0
    ],
    "slice-38": [
      1883648.0,
      25088.0
    ],
    "slice-380": [
      18763264.0,
      7168.0
    ],
    "slice-381": [
      18770432.0,
      20480.0
    ],
    "slice-382": [
      18790912.0,
      7168.0
    ],
    "slice-383": [
      18798080.0,
      9216.0
    ],
    "slice-384": [
      18807296.0,
      13824.0
    ],
    "slice-385": [
      18821120.0,
      13824.0
    ],
    "slice-386": [
      18834944.0,
      13824.0
    ],
    "slice-387": [
      18848768.0,
      8704.0
    ],
    "slice-388": [
      18857472.0,
      9728.0
    ],
    "slice-389": [
      18867200.0,
      6144.0
    ],
    "slice-39": [
      1908736.0,
      222208.0
    ],
    "slice-390": [
      18873344.0,
      29184.0
    ],
    "slice-391": [
      18902528.0,
      9728.0
    ],
    "slice-392": [
      18912256.0,
      16384.0
    ],
    "slice-393": [
      18928640.0,
      131072.0
    ],
    "slice-394": [
      19059712.0,
      11264.0
    ],
    "slice-395": [
      19070976.0,
      7680.0
    ],
    "slice-396": [
      19078656.0,
      22528.0
    ],
    "slice-397": [
      19101184.0,
      60416.0
    ],
    "slice-398": [
      19161600.0,
      62464.0
    ],
    "slice-399": [
      19224064.0,
      55296.0
    ],
    "slice-4": [
      68608.0,
      131072.0
    ],
    "slice-40": [
      2130944.0,
      5632.0
    ],
    "slice-400": [
      19279360.0,
      6656.0
    ],
    "slice-401": [
      19286016.0,
      10240.0
    ],
    "slice-402": [
      19296256.0,
      15360.0
    ],
    "slice-403": [
      19311616.0,
      54272.0
    ],
    "slice-404": [
      19365888.0,
      7168.0
    ],
    "slice-405": [
      19373056.0,
      111616.0
    ],
    "slice-406": [
      19484672.0,
      19968.0
    ],
    "slice-407": [
      19504640.0,
      9728.0
    ],
    "slice-408": [
      19514368.0,
      17920.0
    ],
    "slice-409": [
      19532288.0,
      19456.0
    ],
    "slice-41": [
      2136576.0,
      7680.0
    ],
    "slice-410": [
      19551744.0,
      7168.0
    ],
    "slice-411": [
      19558912.0,
      19968.0
    ],
    "slice-412": [
      19578880.0,
      27136.0
    ],
    "slice-413": [
      19606016.0,
      147968.0
    ],
    "slice-414": [
      19753984.0,
      57344.0
    ],
    "slice-415": [
      19811328.0,
      109568.0
    ],
    "slice-416": [
      19920896.0,
      96768.0
    ],
    "slice-417": [
      20017664.0,
      102912.0
    ],
    "slice-418": [
      20120576.0,
      38912.0
    ],
    "slice-419": [
      20159488.0,
      5632.0
    ],
    "slice-42": [
      2144256.0,
      5632.0
    ],
    "slice-420": [
      20165120.0,
      20992.0
    ],
    "slice-421": [
      20186112.0,
      8192.0
    ],
    "slice-422": [
      20194304.0,
      10240.0
    ],
    "slice-423": [
      20204544.0,
      15872.0
    ],
    "slice-424": [
      20220416.0,
      54784.0
    ],
    "slice-425": [
      20275200.0,
      5632.0
    ],
    "slice-426": [
      20280832.0,
      29184.0
    ],
    "slice-427": [
      20310016.0,
      10240.0
    ],
    "slice-428": [
      20320256.0,
      15872.0
    ],
    "slice-429": [
      20336128.0,
      131584.0
    ],
    "slice-43": [
      2149888.0,
      38400.0
    ],
    "slice-430": [
      20467712.0,
      10752.0
    ],
    "slice-431": [
      20478464.0,
      7680.0
    ],
    "slice-432": [
      20486144.0,
      22528.0
    ],
    "slice-433": [
      20508672.0,
      60416.0
    ],
    "slice-434": [
      20569088.0,
      40448.0
    ],
    "slice-435": [
      20609536.0,
      5632.0
    ],
    "slice-436": [
      20615168.0,
      21504.0
    ],
    "slice-437": [
      20636672.0,
      7680.0
    ],
    "slice-438": [
      20644352.0,
      10240.0
    ],
    "slice-439": [
      20654592.0,
      15872.0
    ],
    "slice-44": [
      2188288.0,
      9216.0
    ],
    "slice-440": [
      20670464.0,
      131584.0
    ],
    "slice-441": [
      20802048.0,
      10752.0
    ],
    "slice-442": [
      20812800.0,
      7680.0
    ],
    "slice-443": [
      20820480.0,
      22528.0
    ],
    "slice-444": [
      20843008.0,
      60416.0
    ],
    "slice-445": [
      20903424.0,
      62464.0
    ],
    "slice-446": [
      20965888.0,
      55808.0
    ],
    "slice-447": [
      21021696.0,
      6656.0
    ],
    "slice-448": [
      21028352.0,
      9728.0
    ],
    "slice-449": [
      21038080.0,
      15360.0
    ],
    "slice-45": [
      2197504.0,
      208896.0
    ],
    "slice-450": [
      21053440.0,
      54272.0
    ],
    "slice-451": [
      21107712.0,
      7168.0
    ],
    "slice-452": [
      21114880.0,
      112128.0
    ],
    "slice-453": [
      21227008.0,
      19456.0
    ],
    "slice-454": [
      21246464.0,
      9728.0
    ],
    "slice-455": [
      21256192.0,
      17920.0
    ],
    "slice-456": [
      21274112.0,
      6656.0
    ],
    "slice-457": [
      21280768.0,
      12800.0
    ],
    "slice-458": [
      21293568.0,
      7680.0
    ],
    "slice-459": [
      21301248.0,
      19968.0
    ],
    "slice-46": [
      2406400.0,
      29696.0
    ],
    "slice-460": [
      21321216.0,
      27136.0
    ],
    "slice-461": [
      21348352.0,
      10752.0
    ],
    "slice-462": [
      21359104.0,
      7168.0
    ],
    "slice-463": [
      21366272.0,
      129536.0
    ],
    "slice-464": [
      21495808.0,
      57344.0
    ],
    "slice-465": [
      21553152.0,
      110080.0
    ],
    "slice-466": [
      21663232.0,
      96256.0
    ],
    "slice-467": [
      21759488.0,
      103424.0
    ],
    "slice-468": [
      21862912.0,
      113664.0
    ],
    "slice-469": [
      21976576.0,
      43008.0
    ],
    "slice-47": [
      2436096.0,
      26112.0
    ],
    "slice-470": [
      22019584.0,
      113664.0
    ],
    "slice-471": [
      22133248.0,
      140288.0
    ],
    "slice-472": [
      22273536.0,
      13824.0
    ],
    "slice-473": [
      22287360.0,
      112128.0
    ],
    "slice-474": [
      22399488.0,
      195072.0
    ],
    "slice-475": [
      22594560.0,
      11776.0
    ],
    "slice-476": [
      22606336.0,
      8704.0
    ],
    "slice-477": [
      22615040.0,
      25088.0
    ],
    "slice-478": [
      22640128.0,
      222208.0
    ],
    "slice-479": [
      22862336.0,
      5632.0
    ],
    "slice-48": [
      2462208.0,
      89600.0
    ],
    "slice-480": [
      22867968.0,
      7680.0
    ],
    "slice-481": [
      22875648.0,
      6144.0
    ],
    "slice-482": [
      22881792.0,
      37888.0
    ],
    "slice-483": [
      22919680.0,
      9216.0
    ],
    "slice-484": [
      22928896.0,
      208896.0
    ],
    "slice-485": [
      23137792.0,
      29696.0
    ],
    "slice-486": [
      23167488.0,
      26112.0
    ],
    "slice-487": [
      23193600.0,
      189952.0
    ],
    "slice-488": [
      23383552.0,
      22016.0
    ],
    "slice-489": [
      23405568.0,
      90112.0
    ],
    "slice-49": [
      2551808.0,
      21504.0
    ],
    "slice-490": [
      23495680.0,
      22016.0
    ],
    "slice-491": [
      23517696.0,
      28672.0
    ],
    "slice-492": [
      23546368.0,
      10240.0
    ],
    "slice-493": [
      23556608.0,
      35840.0
    ],
    "slice-494": [
      23592448.0,
      22016.0
    ],
    "slice-495": [
      23614464.0,
      147968.0
    ],
    "slice-496": [
      23762432.0,
      118272.0
    ],
    "slice-497": [
      23880704.0,
      81408.0
    ],
    "slice-498": [
      23962112.0,
      86016.0
    ],
    "slice-499": [
      24048128.0,
      76800.0
    ],
    "slice-5": [
      199680.0,
      11264.0
    ],
    "slice-50": [
      2573312.0,
      90112.0
    ],
    "slice-500": [
      24124928.0,
      49152.0
    ],
    "slice-501": [
      24174080.0,
      34304.0
    ],
    "slice-502": [
      24208384.0,
      47104.0
    ],
    "slice-503": [
      24255488.0,
      51712.0
    ],
    "slice-504": [
      24307200.0,
      48640.0
    ],
    "slice-505": [
      24355840.0,
      17920.0
    ],
    "slice-506": [
      24373760.0,
      332288.0
    ],
    "slice-507": [
      24706048.0,
      43520.0
    ],
    "slice-508": [
      24749568.0,
      59904.0
    ],
    "slice-509": [
      24809472.0,
      20992.0
    ],
    "slice-51": [
      2663424.0,
      22528.0
    ],
    "slice-510": [
      24830464.0,
      213504.0
    ],
    "slice-511": [
      25043968.0,
      5632.0
    ],
    "slice-512": [
      25049600.0,
      121344.0
    ],
    "slice-513": [
      25170944.0,
      56832.0
    ],
    "slice-514": [
      25227776.0,
      67584.0
    ],
    "slice-515": [
      25295360.0,
      10240.0
    ],
    "slice-516": [
      25305600.0,
      12800.0
    ],
    "slice-517": [
      25318400.0,
      90624.0
    ],
    "slice-518": [
      25409024.0,
      10240.0
    ],
    "slice-519": [
      25419264.0,
      60416.0
    ],
    "slice-52": [
      2685952.0,
      28160.0
    ],
    "slice-520": [
      25479680.0,
      236032.0
    ],
    "slice-521": [
      25715712.0,
      47104.0
    ],
    "slice-522": [
      25762816.0,
      102400.0
    ],
    "slice-523": [
      25865216.0,
      6144.0
    ],
    "slice-524": [
      25871360.0,
      12800.0
    ],
    "slice-525": [
      25884160.0,
      10752.0
    ],
    "slice-526": [
      25894912.0,
      26112.0
    ],
    "slice-527": [
      25921024.0,
      7680.0
    ],
    "slice-528": [
      25928704.0,
      207360.0
    ],
    "slice-529": [
      26136064.0,
      22528.0
    ],
    "slice-53": [
      2714112.0,
      10752.0
    ],
    "slice-530": [
      26158592.0,
      56832.0
    ],
    "slice-531": [
      26215424.0,
      319488.0
    ],
    "slice-532": [
      26534912.0,
      222208.0
    ],
    "slice-533": [
      26757120.0,
      18432.0
    ],
    "slice-534": [
      26775552.0,
      74752.0
    ],
    "slice-535": [
      26850304.0,
      153600.0
    ],
    "slice-536": [
      27003904.0,
      68608.0
    ],
    "slice-537": [
      27072512.0,
      23552.0
    ],
    "slice-538": [
      27096064.0,
      39424.0
    ],
    "slice-539": [
      27135488.0,
      172032.0
    ],
    "slice-54": [
      2724864.0,
      35328.0
    ],
    "slice-540": [
      27307520.0,
      155136.0
    ],
    "slice-541": [
      27462656.0,
      202752.0
    ],
    "slice-542": [
      27665408.0,
      132608.0
    ],
    "slice-543": [
      27798016.0,
      182272.0
    ],
    "slice-544": [
      27980288.0,
      44032.0
    ],
    "slice-545": [
      28024320.0,
      13312.0
    ],
    "slice-546": [
      28037632.0,
      7680.0
    ],
    "slice-547": [
      28045312.0,
      11264.0
    ],
    "slice-548": [
      28056576.0,
      62976.0
    ],
    "slice-549": [
      28119552.0,
      40448.0
    ],
    "slice-55": [
      2760192.0,
      22016.0
    ],
    "slice-550": [
      28160000.0,
      27648.0
    ],
    "slice-551": [
      28187648.0,
      62976.0
    ],
    "slice-552": [
      28250624.0,
      110080.0
    ],
    "slice-553": [
      28360704.0,
      19456.0
    ],
    "slice-554": [
      28380160.0,
      118272.0
    ],
    "slice-555": [
      28498432.0,
      48128.0
    ],
    "slice-556": [
      28546560.0,
      66560.0
    ],
    "slice-557": [
      28613120.0,
      30208.0
    ],
    "slice-558": [
      28643328.0,
      50176.0
    ],
    "slice-559": [
      28693504.0,
      34304.0
    ],
    "slice-56": [
      2782208.0,
      147968.0
    ],
    "slice-560": [
      28727808.0,
      24064.0
    ],
    "slice-561": [
      28751872.0,
      16384.0
    ],
    "slice-562": [
      28768256.0,
      83456.0
    ],
    "slice-563": [
      28851712.0,
      12288.0
    ],
    "slice-564": [
      28864000.0,
      10240.0
    ],
    "slice-565": [
      28874240.0,
      11264.0
    ],
    "slice-566": [
      28885504.0,
      71680.0
    ],
    "slice-567": [
      28957184.0,
      33280.0
    ],
    "slice-568": [
      28990464.0,
      44032.0
    ],
    "slice-569": [
      29034496.0,
      15872.0
    ],
    "slice-57": [
      2930176.0,
      118272.0
    ],
    "slice-570": [
      29050368.0,
      47616.0
    ],
    "slice-571": [
      29097984.0,
      11264.0
    ],
    "slice-572": [
      29109248.0,
      42496.0
    ],
    "slice-573": [
      29151744.0,
      180224.0
    ],
    "slice-574": [
      29331968.0,
      6656.0
    ],
    "slice-575": [
      29338624.0,
      13824.0
    ],
    "slice-576": [
      29352448.0,
      5632.0
    ],
    "slice-577": [
      29358080.0,
      16896.0
    ],
    "slice-578": [
      29374976.0,
      17408.0
    ],
    "slice-579": [
      29392384.0,
      18432.0
    ],
    "slice-58": [
      3048448.0,
      81920.0
    ],
    "slice-580": [
      29410816.0,
      29184.0
    ],
    "slice-581": [
      29440000.0,
      16384.0
    ],
    "slice-582": [
      29456384.0,
      41984.0
    ],
    "slice-583": [
      29498368.0,
      21504.0
    ],
    "slice-584": [
      29519872.0,
      35328.0
    ],
    "slice-585": [
      29555200.0,
      11264.0
    ],
    "slice-586": [
      29566464.0,
      17920.0
    ],
    "slice-587": [
      29584384.0,
      39424.0
    ],
    "slice-588": [
      29623808.0,
      10752.0
    ],
    "slice-589": [
      29634560.0,
      17408.0
    ],
    "slice-59": [
      3130368.0,
      85504.0
    ],
    "slice-590": [
      29651968.0,
      10240.0
    ],
    "slice-591": [
      29662208.0,
      5632.0
    ],
    "slice-592": [
      29667840.0,
      25600.0
    ],
    "slice-593": [
      29693440.0,
      22016.0
    ],
    "slice-594": [
      29715456.0,
      14848.0
    ],
    "slice-595": [
      29730304.0,
      20480.0
    ],
    "slice-596": [
      29750784.0,
      18432.0
    ],
    "slice-597": [
      29769216.0,
      20480.0
    ],
    "slice-598": [
      29789696.0,
      35328.0
    ],
    "slice-599": [
      29825024.0,
      11264.0
    ],
    "slice-6": [
      210944.0,
      7168.0
    ],
    "slice-60": [
      3215872.0,
      76800.0
    ],
    "slice-600": [
      29836288.0,
      10240.0
    ],
    "slice-601": [
      29846528.0,
      11776.0
    ],
    "slice-602": [
      29858304.0,
      15872.0
    ],
    "slice-603": [
      29874176.0,
      16384.0
    ],
    "slice-604": [
      29890560.0,
      19456.0
    ],
    "slice-605": [
      29910016.0,
      16384.0
    ],
    "slice-606": [
      29926400.0,
      11264.0
    ],
    "slice-607": [
      29937664.0,
      6144.0
    ],
    "slice-608": [
      29943808.0,
      11264.0
    ],
    "slice-609": [
      29955072.0,
      19456.0
    ],
    "slice-61": [
      3292672.0,
      49664.0
    ],
    "slice-610": [
      29974528.0,
      86016.0
    ],
    "slice-611": [
      30060544.0,
      10240.0
    ],
    "slice-612": [
      30070784.0,
      22528.0
    ],
    "slice-613": [
      30093312.0,
      54784.0
    ],
    "slice-614": [
      30148096.0,
      79360.0
    ],
    "slice-615": [
      30227456.0,
      8704.0
    ],
    "slice-616": [
      30236160.0,
      74240.0
    ],
    "slice-617": [
      30310400.0,
      13824.0
    ],
    "slice-618": [
      30324224.0,
      79872.0
    ],
    "slice-619": [
      30404096.0,
      23040.0
    ],
    "slice-62": [
      3342336.0,
      33792.0
    ],
    "slice-620": [
      30427136.0,
      61952.0
    ],
    "slice-621": [
      30489088.0,
      36864.0
    ],
    "slice-622": [
      30525952.0,
      81408.0
    ],
    "slice-623": [
      30607360.0,
      28160.0
    ],
    "slice-624": [
      30635520.0,
      19968.0
    ],
    "slice-625": [
      30655488.0,
      82432.0
    ],
    "slice-626": [
      30737920.0,
      57344.0
    ],
    "slice-627": [
      30795264.0,
      32256.0
    ],
    "slice-628": [
      30827520.0,
      78848.0
    ],
    "slice-629": [
      30906368.0,
      53760.0
    ],
    "slice-63": [
      3376128.0,
      47616.0
    ],
    "slice-630": [
      30960128.0,
      24576.0
    ],
    "slice-631": [
      30984704.0,
      6144.0
    ],
    "slice-632": [
      30990848.0,
      165376.0
    ],
    "slice-633": [
      31156224.0,
      19968.0
    ],
    "slice-634": [
      31176192.0,
      23552.0
    ],
    "slice-635": [
      31199744.0,
      38912.0
    ],
    "slice-636": [
      31238656.0,
      124416.0
    ],
    "slice-637": [
      31363072.0,
      47104.0
    ],
    "slice-638": [
      31410176.0,
      25600.0
    ],
    "slice-639": [
      31435776.0,
      21504.0
    ],
    "slice-64": [
      3423744.0,
      51712.0
    ],
    "slice-640": [
      31457280.0,
      22016.0
    ],
    "slice-641": [
      31479296.0,
      176640.0
    ],
    "slice-642": [
      31655936.0,
      143360.0
    ],
    "slice-643": [
      31799296.0,
      75264.0
    ],
    "slice-644": [
      31874560.0,
      100352.0
    ],
    "slice-645": [
      31974912.0,
      36352.0
    ],
    "slice-646": [
      32011264.0,
      6144.0
    ],
    "slice-647": [
      32017408.0,
      6656.0
    ],
    "slice-648": [
      32024064.0,
      129536.0
    ],
    "slice-649": [
      32153600.0,
      15872.0
    ],
    "slice-65": [
      3475456.0,
      48640.0
    ],
    "slice-650": [
      32169472.0,
      47104.0
    ],
    "slice-651": [
      32216576.0,
      60928.0
    ],
    "slice-652": [
      32277504.0,
      19456.0
    ],
    "slice-653": [
      32296960.0,
      14848.0
    ],
    "slice-654": [
      32311808.0,
      116224.0
    ],
    "slice-655": [
      32428032.0,
      12800.0
    ],
    "slice-656": [
      32440832.0,
      31232.0
    ],
    "slice-657": [
      32472064.0,
      21504.0
    ],
    "slice-658": [
      32493568.0,
      7680.0
    ],
    "slice-659": [
      32501248.0,
      13824.0
    ],
    "slice-66": [
      3524096.0,
      350208.0
    ],
    "slice-660": [
      32515072.0,
      6656.0
    ],
    "slice-661": [
      32521728.0,
      174592.0
    ],
    "slice-662": [
      32696320.0,
      6656.0
    ],
    "slice-663": [
      32702976.0,
      21504.0
    ],
    "slice-664": [
      32724480.0,
      10752.0
    ],
    "slice-665": [
      32735232.0,
      9216.0
    ],
    "slice-666": [
      32744448.0,
      117248.0
    ],
    "slice-667": [
      32861696.0,
      7680.0
    ],
    "slice-668": [
      32869376.0,
      19456.0
    ],
    "slice-669": [
      32888832.0,
      8704.0
    ],
    "slice-67": [
      3874304.0,
      104448.0
    ],
    "slice-670": [
      32897536.0,
      61952.0
    ],
    "slice-671": [
      32959488.0,
      5632.0
    ],
    "slice-672": [
      32965120.0,
      98304.0
    ],
    "slice-673": [
      33063424.0,
      7680.0
    ],
    "slice-674": [
      33071104.0,
      94720.0
    ],
    "slice-675": [
      33165824.0,
      6144.0
    ],
    "slice-676": [
      33171968.0,
      8192.0
    ],
    "slice-677": [
      33180160.0,
      24064.0
    ],
    "slice-678": [
      33204224.0,
      6656.0
    ],
    "slice-679": [
      33210880.0,
      201728.0
    ],
    "slice-68": [
      3978752.0,
      27648.0
    ],
    "slice-680": [
      33412608.0,
      8704.0
    ],
    "slice-681": [
      33421312.0,
      20992.0
    ],
    "slice-682": [
      33442304.0,
      128000.0
    ],
    "slice-683": [
      33570304.0,
      67584.0
    ],
    "slice-684": [
      33637888.0,
      10752.0
    ],
    "slice-685": [
      33648640.0,
      13824.0
    ],
    "slice-686": [
      33662464.0,
      11264.0
    ],
    "slice-687": [
      33673728.0,
      15360.0
    ],
    "slice-688": [
      33689088.0,
      29184.0
    ],
    "slice-689": [
      33718272.0,
      141824.0
    ],
    "slice-69": [
      4006400.0,
      205824.0
    ],
    "slice-690": [
      33860096.0,
      6144.0
    ],
    "slice-691": [
      33866240.0,
      6656.0
    ],
    "slice-692": [
      33872896.0,
      13312.0
    ],
    "slice-693": [
      33886208.0,
      15360.0
    ],
    "slice-694": [
      33901568.0,
      8704.0
    ],
    "slice-695": [
      33910272.0,
      7168.0
    ],
    "slice-696": [
      33917440.0,
      9728.0
    ],
    "slice-697": [
      33927168.0,
      10240.0
    ],
    "slice-698": [
      33937408.0,
      10240.0
    ],
    "slice-699": [
      33947648.0,
      12288.0
    ],
    "slice-7": [
      218112.0,
      22528.0
    ],
    "slice-70": [
      4212224.0,
      179712.0
    ],
    "slice-700": [
      33959936.0,
      9216.0
    ],
    "slice-701": [
      33969152.0,
      5632.0
    ],
    "slice-702": [
      33974784.0,
      5632.0
    ],
    "slice-703": [
      33980416.0,
      9216.0
    ],
    "slice-704": [
      33989632.0,
      9728.0
    ],
    "slice-705": [
      33999360.0,
      57344.0
    ],
    "slice-706": [
      34056704.0,
      22016.0
    ],
    "slice-707": [
      34078720.0,
      139776.0
    ],
    "slice-708": [
      34218496.0,
      8704.0
    ],
    "slice-709": [
      34227200.0,
      19456.0
    ],
    "slice-71": [
      4391936.0,
      71168.0
    ],
    "slice-710": [
      34246656.0,
      19456.0
    ],
    "slice-711": [
      34266112.0,
      6656.0
    ],
    "slice-712": [
      34272768.0,
      6656.0
    ],
    "slice-713": [
      34279424.0,
      32768.0
    ],
    "slice-714": [
      34312192.0,
      6656.0
    ],
    "slice-715": [
      34318848.0,
      8192.0
    ],
    "slice-716": [
      34327040.0,
      11264.0
    ],
    "slice-717": [
      34338304.0,
      162816.0
    ],
    "slice-718": [
      34501120.0,
      9728.0
    ],
    "slice-719": [
      34510848.0,
      108032.0
    ],
    "slice-72": [
      4463104.0,
      10240.0
    ],
    "slice-720": [
      34618880.0,
      58880.0
    ],
    "slice-721": [
      34677760.0,
      13312.0
    ],
    "slice-722": [
      34691072.0,
      18944.0
    ],
    "slice-723": [
      34710016.0,
      55808.0
    ],
    "slice-724": [
      34765824.0,
      13824.0
    ],
    "slice-725": [
      34779648.0,
      6656.0
    ],
    "slice-726": [
      34786304.0,
      77312.0
    ],
    "slice-727": [
      34863616.0,
      43520.0
    ],
    "slice-728": [
      34907136.0,
      38400.0
    ],
    "slice-729": [
      34945536.0,
      145920.0
    ],
    "slice-73": [
      4473344.0,
      12800.0
    ],
    "slice-730": [
      35091456.0,
      30208.0
    ],
    "slice-731": [
      35121664.0,
      6144.0
    ],
    "slice-732": [
      35127808.0,
      12288.0
    ],
    "slice-733": [
      35140096.0,
      13312.0
    ],
    "slice-734": [
      35153408.0,
      179200.0
    ],
    "slice-735": [
      35332608.0,
      8704.0
    ],
    "slice-736": [
      35341312.0,
      13312.0
    ],
    "slice-737": [
      35354624.0,
      10240.0
    ],
    "slice-738": [
      35364864.0,
      7680.0
    ],
    "slice-739": [
      35372544.0,
      11264.0
    ],
    "slice-74": [
      4486144.0,
      91136.0
    ],
    "slice-740": [
      35383808.0,
      6144.0
    ],
    "slice-741": [
      35389952.0,
      94720.0
    ],
    "slice-742": [
      35484672.0,
      29184.0
    ],
    "slice-743": [
      35513856.0,
      70144.0
    ],
    "slice-744": [
      35584000.0,
      119296.0
    ],
    "slice-745": [
      35703296.0,
      7680.0
    ],
    "slice-746": [
      35710976.0,
      82944.0
    ],
    "slice-747": [
      35793920.0,
      6144.0
    ],
    "slice-748": [
      35800064.0,
      7680.0
    ],
    "slice-749": [
      35807744.0,
      26624.0
    ],
    "slice-75": [
      4577280.0,
      9728.0
    ],
    "slice-750": [
      35834368.0,
      6144.0
    ],
    "slice-751": [
      35840512.0,
      8192.0
    ],
    "slice-752": [
      35848704.0,
      197120.0
    ],
    "slice-753": [
      36045824.0,
      9728.0
    ],
    "slice-754": [
      36055552.0,
      9216.0
    ],
    "slice-755": [
      36064768.0,
      129024.0
    ],
    "slice-756": [
      36193792.0,
      27136.0
    ],
    "slice-757": [
      36220928.0,
      9216.0
    ],
    "slice-758": [
      36230144.0,
      94208.0
    ],
    "slice-759": [
      36324352.0,
      10752.0
    ],
    "slice-76": [
      4587008.0,
      60928.0
    ],
    "slice-760": [
      36335104.0,
      9728.0
    ],
    "slice-761": [
      36344832.0,
      68096.0
    ],
    "slice-762": [
      36412928.0,
      18944.0
    ],
    "slice-763": [
      36431872.0,
      141824.0
    ],
    "slice-764": [
      36573696.0,
      6144.0
    ],
    "slice-765": [
      36579840.0,
      36352.0
    ],
    "slice-766": [
      36616192.0,
      10752.0
    ],
    "slice-767": [
      36626944.0,
      5632.0
    ],
    "slice-768": [
      36632576.0,
      11264.0
    ],
    "slice-769": [
      36643840.0,
      26112.0
    ],
    "slice-77": [
      4647936.0,
      181248.0
    ],
    "slice-770": [
      36669952.0,
      7680.0
    ],
    "slice-771": [
      36677632.0,
      5632.0
    ],
    "slice-772": [
      36683264.0,
      16384.0
    ],
    "slice-773": [
      36699648.0,
      15872.0
    ],
    "slice-774": [
      36715520.0,
      148992.0
    ],
    "slice-775": [
      36864512.0,
      109056.0
    ],
    "slice-776": [
      36973568.0,
      7168.0
    ],
    "slice-777": [
      36980736.0,
      13824.0
    ],
    "slice-778": [
      36994560.0,
      16896.0
    ],
    "slice-779": [
      37011456.0,
      37888.0
    ],
    "slice-78": [
      4829184.0,
      54272.0
    ],
    "slice-780": [
      37049344.0,
      31744.0
    ],
    "slice-781": [
      37081088.0,
      8192.0
    ],
    "slice-782": [
      37089280.0,
      335872.0
    ],
    "slice-783": [
      37425152.0,
      95232.0
    ],
    "slice-784": [
      37520384.0,
      15872.0
    ],
    "slice-785": [
      37536256.0,
      6656.0
    ],
    "slice-786": [
      37542912.0,
      14336.0
    ],
    "slice-787": [
      37557248.0,
      8704.0
    ],
    "slice-788": [
      37565952.0,
      24576.0
    ],
    "slice-789": [
      37590528.0,
      10240.0
    ],
    "slice-79": [
      4883456.0,
      154112.0
    ],
    "slice-790": [
      37600768.0,
      94720.0
    ],
    "slice-791": [
      37695488.0,
      6144.0
    ],
    "slice-792": [
      37701632.0,
      10240.0
    ],
    "slice-793": [
      37711872.0,
      122880.0
    ],
    "slice-794": [
      37834752.0,
      75776.0
    ],
    "slice-795": [
      37910528.0,
      25088.0
    ],
    "slice-796": [
      37935616.0,
      30208.0
    ],
    "slice-797": [
      37965824.0,
      24576.0
    ],
    "slice-798": [
      37990400.0,
      19456.0
    ],
    "slice-799": [
      38009856.0,
      60416.0
    ],
    "slice-8": [
      240640.0,
      60416.0
    ],
    "slice-80": [
      5037568.0,
      11776.0
    ],
    "slice-800": [
      38070272.0,
      17408.0
    ],
    "slice-801": [
      38087680.0,
      76288.0
    ],
    "slice-802": [
      38163968.0,
      55808.0
    ],
    "slice-803": [
      38219776.0,
      8704.0
    ],
    "slice-804": [
      38228480.0,
      7168.0
    ],
    "slice-805": [
      38235648.0,
      7680.0
    ],
    "slice-806": [
      38243328.0,
      11776.0
    ],
    "slice-807": [
      38255104.0,
      13312.0
    ],
    "slice-808": [
      38268416.0,
      42496.0
    ],
    "slice-809": [
      38310912.0,
      14848.0
    ],
    "slice-81": [
      5049344.0,
      6656.0
    ],
    "slice-810": [
      38325760.0,
      47104.0
    ],
    "slice-811": [
      38372864.0,
      8704.0
    ],
    "slice-812": [
      38381568.0,
      24576.0
    ],
    "slice-813": [
      38406144.0,
      14848.0
    ],
    "slice-814": [
      38420992.0,
      10240.0
    ],
    "slice-815": [
      38431232.0,
      8704.0
    ],
    "slice-816": [
      38439936.0,
      8192.0
    ],
    "slice-817": [
      38448128.0,
      10752.0
    ],
    "slice-818": [
      38458880.0,
      15360.0
    ],
    "slice-819": [
      38474240.0,
      14336.0
    ],
    "slice-82": [
      5056000.0,
      6656.0
    ],
    "slice-820": [
      38488576.0,
      6656.0
    ],
    "slice-821": [
      38495232.0,
      6144.0
    ],
    "slice-822": [
      38501376.0,
      15360.0
    ],
    "slice-823": [
      38516736.0,
      16384.0
    ],
    "slice-824": [
      38533120.0,
      18432.0
    ],
    "slice-825": [
      38551552.0,
      28672.0
    ],
    "slice-826": [
      38580224.0,
      16384.0
    ],
    "slice-827": [
      38596608.0,
      36352.0
    ],
    "slice-828": [
      38632960.0,
      5632.0
    ],
    "slice-829": [
      38638592.0,
      7680.0
    ],
    "slice-83": [
      5062656.0,
      30208.0
    ],
    "slice-830": [
      38646272.0,
      8192.0
    ],
    "slice-831": [
      38654464.0,
      8704.0
    ],
    "slice-832": [
      38663168.0,
      10752.0
    ],
    "slice-833": [
      38673920.0,
      12800.0
    ],
    "slice-834": [
      38686720.0,
      34816.0
    ],
    "slice-835": [
      38721536.0,
      19968.0
    ],
    "slice-836": [
      38741504.0,
      17920.0
    ],
    "slice-837": [
      38759424.0,
      13824.0
    ],
    "slice-838": [
      38773248.0,
      21504.0
    ],
    "slice-839": [
      38794752.0,
      26112.0
    ],
    "slice-84": [
      5092864.0,
      210944.0
    ],
    "slice-840": [
      38820864.0,
      16896.0
    ],
    "slice-841": [
      38837760.0,
      25600.0
    ],
    "slice-842": [
      38863360.0,
      17920.0
    ],
    "slice-843": [
      38881280.0,
      13312.0
    ],
    "slice-844": [
      38894592.0,
      7168.0
    ],
    "slice-845": [
      38901760.0,
      25088.0
    ],
    "slice-846": [
      38926848.0,
      8704.0
    ],
    "slice-847": [
      38935552.0,
      6144.0
    ],
    "slice-848": [
      38941696.0,
      7168.0
    ],
    "slice-849": [
      38948864.0,
      17408.0
    ],
    "slice-85": [
      5303808.0,
      23040.0
    ],
    "slice-850": [
      38966272.0,
      8192.0
    ],
    "slice-851": [
      38974464.0,
      10240.0
    ],
    "slice-852": [
      38984704.0,
      16384.0
    ],
    "slice-853": [
      39001088.0,
      14336.0
    ],
    "slice-854": [
      39015424.0,
      25088.0
    ],
    "slice-855": [
      39040512.0,
      30208.0
    ],
    "slice-856": [
      39070720.0,
      10240.0
    ],
    "slice-857": [
      39080960.0,
      29184.0
    ],
    "slice-858": [
      39110144.0,
      137216.0
    ],
    "slice-859": [
      39247360.0,
      24064.0
    ],
    "slice-86": [
      5326848.0,
      56832.0
    ],
    "slice-860": [
      39271424.0,
      9728.0
    ],
    "slice-861": [
      39281152.0,
      10752.0
    ],
    "slice-862": [
      39291904.0,
      19968.0
    ],
    "slice-863": [
      39311872.0,
      8192.0
    ],
    "slice-864": [
      39320064.0,
      216576.0
    ],
    "slice-865": [
      39536640.0,
      13824.0
    ],
    "slice-866": [
      39550464.0,
      9728.0
    ],
    "slice-867": [
      39560192.0,
      5632.0
    ],
    "slice-868": [
      39565824.0,
      10240.0
    ],
    "slice-869": [
      39576064.0,
      11264.0
    ],
    "slice-87": [
      5383680.0,
      320000.0
    ],
    "slice-870": [
      39587328.0,
      34816.0
    ],
    "slice-871": [
      39622144.0,
      36864.0
    ],
    "slice-872": [
      39659008.0,
      132096.0
    ],
    "slice-873": [
      39791104.0,
      113664.0
    ],
    "slice-874": [
      39904768.0,
      39424.0
    ],
    "slice-875": [
      39944192.0,
      18944.0
    ],
    "slice-876": [
      39963136.0,
      8192.0
    ],
    "slice-877": [
      39971328.0,
      8192.0
    ],
    "slice-878": [
      39979520.0,
      91648.0
    ],
    "slice-879": [
      40071168.0,
      11776.0
    ],
    "slice-88": [
      5703680.0,
      221184.0
    ],
    "slice-880": [
      40082944.0,
      40960.0
    ],
    "slice-881": [
      40123904.0,
      5632.0
    ],
    "slice-882": [
      40129536.0,
      82432.0
    ],
    "slice-883": [
      40211968.0,
      116224.0
    ],
    "slice-884": [
      40328192.0,
      79360.0
    ],
    "slice-885": [
      40407552.0,
      184320.0
    ],
    "slice-886": [
      40591872.0,
      131584.0
    ],
    "slice-887": [
      40723456.0,
      55808.0
    ],
    "slice-888": [
      40779264.0,
      14336.0
    ],
    "slice-889": [
      40793600.0,
      130560.0
    ],
    "slice-89": [
      5924864.0,
      18432.0
    ],
    "slice-890": [
      40924160.0,
      157184.0
    ],
    "slice-891": [
      41081344.0,
      9216.0
    ],
    "slice-892": [
      41090560.0,
      22016.0
    ],
    "slice-893": [
      41112576.0,
      30208.0
    ],
    "slice-894": [
      41142784.0,
      385024.0
    ],
    "slice-895": [
      41527808.0,
      22528.0
    ],
    "slice-896": [
      41550336.0,
      27136.0
    ],
    "slice-897": [
      41577472.0,
      207360.0
    ],
    "slice-898": [
      41784832.0,
      20992.0
    ],
    "slice-899": [
      41805824.0,
      13312.0
    ],
    "slice-9": [
      301056.0,
      62976.0
    ],
    "slice-90": [
      5943296.0,
      10240.0
    ],
    "slice-900": [
      41819136.0,
      7680.0
    ],
    "slice-901": [
      41826816.0,
      15872.0
    ],
    "slice-902": [
      41842688.0,
      20480.0
    ],
    "slice-903": [
      41863168.0,
      7168.0
    ],
    "slice-904": [
      41870336.0,
      20480.0
    ],
    "slice-905": [
      41890816.0,
      7168.0
    ],
    "slice-906": [
      41897984.0,
      9216.0
    ],
    "slice-907": [
      41907200.0,
      13824.0
    ],
    "slice-908": [
      41921024.0,
      13824.0
    ],
    "slice-909": [
      41934848.0,
      13312.0
    ],
    "slice-91": [
      5953536.0,
      64512.0
    ],
    "slice-910": [
      41948160.0,
      9216.0
    ],
    "slice-911": [
      41957376.0,
      9216.0
    ],
    "slice-912": [
      41966592.0,
      7168.0
    ],
    "slice-913": [
      41973760.0,
      25600.0
    ],
    "slice-914": [
      41999360.0,
      13312.0
    ],
    "slice-915": [
      42012672.0,
      23040.0
    ],
    "slice-916": [
      42035712.0,
      11776.0
    ],
    "slice-917": [
      42047488.0,
      9216.0
    ],
    "slice-918": [
      42056704.0,
      9728.0
    ],
    "slice-919": [
      42066432.0,
      17408.0
    ],
    "slice-92": [
      6018048.0,
      154112.0
    ],
    "slice-920": [
      42083840.0,
      9216.0
    ],
    "slice-921": [
      42093056.0,
      12288.0
    ],
    "slice-922": [
      42105344.0,
      9216.0
    ],
    "slice-923": [
      42114560.0,
      6656.0
    ],
    "slice-924": [
      42121216.0,
      7168.0
    ],
    "slice-925": [
      42128384.0,
      11776.0
    ],
    "slice-926": [
      42140160.0,
      27136.0
    ],
    "slice-927": [
      42167296.0,
      7168.0
    ],
    "slice-928": [
      42174464.0,
      6656.0
    ],
    "slice-929": [
      42181120.0,
      11776.0
    ],
    "slice-93": [
      6172160.0,
      68608.0
    ],
    "slice-930": [
      42192896.0,
      11264.0
    ],
    "slice-931": [
      42204160.0,
      7168.0
    ],
    "slice-932": [
      42211328.0,
      15872.0
    ],
    "slice-933": [
      42227200.0,
      16384.0
    ],
    "slice-934": [
      42243584.0,
      13312.0
    ],
    "slice-935": [
      42256896.0,
      18432.0
    ],
    "slice-936": [
      42275328.0,
      7680.0
    ],
    "slice-937": [
      42283008.0,
      6656.0
    ],
    "slice-94": [
      6240768.0,
      23040.0
    ],
    "slice-95": [
      6263808.0,
      39424.0
    ],
    "slice-96": [
      6303232.0,
      172544.0
    ],
    "slice-97": [
      6475776.0,
      154624.0
    ],
    "slice-98": [
      6630400.0,
      203264.0
    ],
    "slice-99": [
      6833664.0,
      132608.0
    ]
  }
}
